anchors/__init__.py
anchors/core.py
anchors/objc_plus.py
anchors/observer.py
anchors/safe_area.py
pythonista_anchors-2020.10.22.dist-info/WHEEL
pythonista_anchors-2020.10.22.dist-info/METADATA
pythonista_anchors-2020.10.22.dist-info/RECORD
