Metadata-Version: 2.1
Name: pythonista-anchors
Version: 2020.10.22
Summary: Pythonista UI constraints driven by the Key Value Observing (KVO) protocol
Home-page: https://github.com/mikaelho/pythonista-anchor
License: TheUnlicense
Author: Mikael Honkala
Author-email: mikael.honkala@gmail.com
Classifier: Operating System :: iOS
